Metadata-Version: 1.1
Name: ngrammatcher
Version: 1.0
Summary: Matches pre-defined ngrams from a given list of words/tokens.
Home-page: http://github.com/jwnz/ngrammatcher
Author: Teryn Jones
Author-email: tkjones93@gmail.com
License: UNKNOWN
Platform: any
Classifier: Programming Language :: Python
Classifier: Programming Language :: Python :: 2.7
Classifier: Programming Language :: Python :: 3
Classifier: Operating System :: OS Independent
Classifier: Intended Audience :: Developers
Classifier: License :: OSI Approved :: MIT License
